pymed/__init__.py
pymed/api.py
pymed/article.py
pymed/book.py
pymed/helpers.py
pymed/version.py
pymed-0.8.9.dist-info/LICENCE
pymed-0.8.9.dist-info/METADATA
pymed-0.8.9.dist-info/WHEEL
pymed-0.8.9.dist-info/top_level.txt
pymed-0.8.9.dist-info/RECORD
