Metadata-Version: 2.1
Name: pymed
Version: 0.8.9
Summary: Python library for access to PubMed
Home-page: https://github.com/gijswobben/pymed
Author: Gijs Wobben
Author-email: gijswobben@gmail.com
License: MIT
Keywords: PubMed PMC
Platform: UNKNOWN
Classifier: Topic :: Utilities
Classifier: Development Status :: 3 - Alpha
Classifier: Intended Audience :: Science/Research
Classifier: License :: OSI Approved :: MIT License
Classifier: Programming Language :: Python :: 3 :: Only
